Metadata-Version: 1.0
Name: dist-nd-lesson
Version: 0.1
Summary: Gaussian and binomial distributions
Home-page: UNKNOWN
Author: Nathan Dennison
Author-email: nathan.dennison@gmail.com
License: UNKNOWN
Platform: UNKNOWN
